versionedfunction/__init__.py
versionedfunction/versionedfunction.py
versionedfunction/versionedfunction_test.py
versionedfunction-0.9.57.dist-info/LICENSE.txt
versionedfunction-0.9.57.dist-info/METADATA
versionedfunction-0.9.57.dist-info/WHEEL
versionedfunction-0.9.57.dist-info/RECORD
